<?xml version="1.0" encoding="UTF-8"?>
<?xml-model href="http://jenkins.tei-c.org/job/TEIP5-dev/lastSuccessfulBuild/artifact/P5/release/xml/tei/odd/p5.nvdl"
    type="application/xml"
    schematypens="http://purl.oclc.org/dsdl/nvdl/ns/structure/1.0"?>
<elementSpec xmlns="http://www.tei-c.org/ns/1.0" ident="pc" module="analysis" mode="change">
  <gloss xml:lang="de" versionDate="2025-02-03">Satzzeichen</gloss>
  <gloss xml:lang="en" versionDate="2025-02-03">punctuation character</gloss>
  <gloss xml:lang="fr" versionDate="2025-02-03">signe de ponctuation</gloss>
  <desc xml:lang="de" versionDate="2025-02-06">Beinhaltet ein Satzzeichen, welches unter
    Berücksichtigung sprachlicher Regelungen besonders verarbeitet wird.</desc>
  <desc xml:lang="en" versionDate="2024-04-30">Contains a punctuation mark, which is processed
    specially considering linguistic regulations (for example, by adding a space).</desc>
  <desc xml:lang="en" versionDate="2025-02-06">Contient un signe de ponctuation spécialement
    traité en tenant compte des réglementations linguistiques.</desc>
  <classes mode="replace"/>
  <content>
    <valList type="closed">
      <valItem ident=";"/>
      <valItem ident=":"/>
      <valItem ident="?"/>
      <valItem ident="!"/>
    </valList>
  </content>
  <attList>
    <attDef ident="force" mode="delete"/>
    <attDef ident="unit" mode="delete"/>
    <attDef ident="pre" mode="delete"/>
  </attList>
  <remarks xml:lang="de" versionDate="2025-02-06">
    <p>Damit eine sprachabhängige Darstellung der Interpunktion möglich ist, werden Satzzeichen,
      die in den unterschiedlichen Sprachen der Edition (v. a. Deutsch und Französisch) anders
      behandelt werden müssen, mit <gi>pc</gi> ausgezeichnet.</p>
  </remarks>
  <remarks xml:lang="fr" versionDate="2025-02-06">
    <p>Afin de permettre une représentation de la ponctuation dépendante de la langue,
      les signes de ponctuation qui doivent être traités différemment dans les différentes
      langues de l’édition (en particulier l’allemand et le français) sont marqués
      avec <gi>pc</gi>.</p>
  </remarks>
</elementSpec>
